.testr.conf
AUTHORS
ChangeLog
README.rst
requirements.txt
setup.cfg
setup.py
test-requirements.txt
tox.ini
bin/neutron-zvm-agent
doc/source/advanced.rst
doc/source/conf.py
doc/source/index.rst
doc/source/singleflat.rst
doc/source/singlevlan.rst
doc/source/images/flatvlan.png
doc/source/images/singleflat.png
etc/neutron/plugins/zvm/neutron_zvm_plugin.ini.sample
neutron/plugins/ml2/drivers/zvm/__init__.py
neutron/plugins/ml2/drivers/zvm/mech_zvm.py
neutron/plugins/zvm/__init__.py
neutron/plugins/zvm/agent/__init__.py
neutron/plugins/zvm/agent/zvm_network.py
neutron/plugins/zvm/agent/zvm_neutron_agent.py
neutron/plugins/zvm/common/__init__.py
neutron/plugins/zvm/common/config.py
neutron/plugins/zvm/common/exception.py
neutron/plugins/zvm/common/utils.py
neutron/tests/unit/plugins/__init__.py
neutron/tests/unit/plugins/ml2/__init__.py
neutron/tests/unit/plugins/ml2/zvm/__init__.py
neutron/tests/unit/plugins/ml2/zvm/test_mech_zvm.py
neutron/tests/unit/plugins/zvm/__init__.py
neutron/tests/unit/plugins/zvm/test_zvm_network.py
neutron/tests/unit/plugins/zvm/test_zvm_neutron_agent.py
neutron/tests/unit/plugins/zvm/test_zvm_utils.py
neutron_zvm_plugin.egg-info/PKG-INFO
neutron_zvm_plugin.egg-info/SOURCES.txt
neutron_zvm_plugin.egg-info/dependency_links.txt
neutron_zvm_plugin.egg-info/entry_points.txt
neutron_zvm_plugin.egg-info/not-zip-safe
neutron_zvm_plugin.egg-info/pbr.json
neutron_zvm_plugin.egg-info/requires.txt
neutron_zvm_plugin.egg-info/top_level.txt
tools/build_rpm.sh
tools/post_install
tools/post_uninstall
tools/pre_uninstall