Metadata-Version: 1.1
Name: neutron-zvm-plugin
Version: 11.0.0
Summary: zVM ML2 mechanism driver and zVM neutron agent.
Home-page: https://wiki.openstack.org/wiki/Networking-zvm
Author: IBM
Author-email: UNKNOWN
License: UNKNOWN
Platform: UNKNOWN
Classifier: Environment :: OpenStack
Classifier: Intended Audience :: Information Technology
Classifier: Intended Audience :: System Administrators
Classifier: License :: OSI Approved :: Apache Software License
Classifier: Operating System :: POSIX :: Linux
Classifier: Programming Language :: Python
Classifier: Programming Language :: Python :: 2
Classifier: Programming Language :: Python :: 2.7
